tests/__init__.py
tests/conftest.py
tests/test_base_api_cache.py
tests/test_base_api_object.py
tests/test_base_api_response.py
tests/test_base_client.py
tests/test_domain.py
tests/test_utils.py
veil_api_client/__init__.py
veil_api_client/https_client.py
veil_api_client/api_objects/__init__.py
veil_api_client/api_objects/cluster.py
veil_api_client/api_objects/controller.py
veil_api_client/api_objects/data_pool.py
veil_api_client/api_objects/domain.py
veil_api_client/api_objects/event.py
veil_api_client/api_objects/library.py
veil_api_client/api_objects/node.py
veil_api_client/api_objects/resource_pool.py
veil_api_client/api_objects/vdisk.py
veil_api_client/base/__init__.py
veil_api_client/base/api_cache.py
veil_api_client/base/api_object.py
veil_api_client/base/api_response.py
veil_api_client/base/utils.py
veil_api_client-2.2.18.dist-info/LICENSE
veil_api_client-2.2.18.dist-info/METADATA
veil_api_client-2.2.18.dist-info/WHEEL
veil_api_client-2.2.18.dist-info/top_level.txt
veil_api_client-2.2.18.dist-info/RECORD
