Metadata-Version: 2.1
Name: veil-api-client
Version: 2.2.18
Summary: VeiL ECP Api client
Home-page: https://github.com/jsc-masshtab/veil-api-client
Author: Aleksey Devyatkin, Emile Gareev
Author-email: a.devyatkin@mashtab.org, e.gareev@mashtab.org
License: UNKNOWN
Platform: UNKNOWN
Classifier: Programming Language :: Python :: 3
Classifier: License :: OSI Approved :: MIT License
Classifier: Development Status :: 5 - Production/Stable
Classifier: Operating System :: OS Independent
Requires-Python: >=3.5
Requires-Dist: aiohttp (==3.6.*)
Requires-Dist: ujson (==3.0.*)
